MANIFEST.in
Makefile
README.rst
README.txt
base.cfg
buildout.cfg
code-analysis.cfg
plone-6.0.x.cfg
requirements.txt
requirements_plone-6.0.x.txt
setup.py
versions.cfg
collective/__init__.py
collective.geotransform.egg-info/PKG-INFO
collective.geotransform.egg-info/SOURCES.txt
collective.geotransform.egg-info/dependency_links.txt
collective.geotransform.egg-info/entry_points.txt
collective.geotransform.egg-info/namespace_packages.txt
collective.geotransform.egg-info/not-zip-safe
collective.geotransform.egg-info/requires.txt
collective.geotransform.egg-info/top_level.txt
collective/geotransform/__init__.py
collective/geotransform/configure.zcml
collective/geotransform/interfaces.py
collective/geotransform/testing.py
collective/geotransform/transform.py
collective/geotransform/profiles/default/browserlayer.xml
collective/geotransform/profiles/default/metadata.xml
collective/geotransform/profiles/default/registry.xml
collective/geotransform/profiles/uninstall/browserlayer.xml
collective/geotransform/static/geoMailDecoder.js
collective/geotransform/static/jquery.base64.min.js
collective/geotransform/tests/__init__.py
collective/geotransform/tests/test_installation.py
collective/geotransform/tests/test_robot.py
collective/geotransform/tests/test_transform.py
collective/geotransform/tests/robot/test_decrypt.robot
docs/HISTORY.txt
docs/INSTALL.txt
docs/LICENSE.GPL
docs/LICENSE.txt