Metadata-Version: 2.1
Name: collective.geotransform
Version: 3.0
Summary: Gracefully email obfuscation for Plone
Home-page: https://github.com/collective/collective.geotransform
Author: Victor Fernandez de Alba
Author-email: sneridagh@gmail.com
License: GPL
Keywords: geo email obfuscation Plone Zope
Platform: UNKNOWN
Classifier: Framework :: Plone
Classifier: Framework :: Plone :: 6.0
Classifier: Programming Language :: Python
Classifier: Programming Language :: Python :: 3.8
Classifier: Programming Language :: Python :: 3.9
Classifier: Programming Language :: Python :: 3.10
Classifier: Programming Language :: Python :: 3.11
Provides-Extra: test
